alpaca/__init__.py
alpaca/broker/__init__.py
alpaca/broker/client.py
alpaca/broker/enums.py
alpaca/broker/models/__init__.py
alpaca/broker/models/accounts.py
alpaca/broker/models/cip.py
alpaca/broker/models/documents.py
alpaca/broker/models/funding.py
alpaca/broker/models/journals.py
alpaca/broker/models/rebalancing.py
alpaca/broker/models/trading.py
alpaca/broker/requests.py
alpaca/common/__init__.py
alpaca/common/constants.py
alpaca/common/enums.py
alpaca/common/exceptions.py
alpaca/common/models.py
alpaca/common/requests.py
alpaca/common/rest.py
alpaca/common/types.py
alpaca/common/utils.py
alpaca/py.typed
alpaca/trading/__init__.py
alpaca/trading/client.py
alpaca/trading/enums.py
alpaca/trading/models.py
alpaca/trading/requests.py
alpaca_py_slim-0.42.0.dist-info/LICENSE
alpaca_py_slim-0.42.0.dist-info/METADATA
alpaca_py_slim-0.42.0.dist-info/WHEEL
alpaca_py_slim-0.42.0.dist-info/RECORD
