Metadata-Version: 2.3
Name: alpaca-py-slim
Version: 0.42.0
Summary: The Official Python SDK for Alpaca APIs - slim version
License: Apache-2.0
Author: Nick Crews
Author-email: nickcrews35@gmail.com
Requires-Python: >=3.8.0,<4.0.0
Classifier: License :: OSI Approved :: Apache Software License
Classifier: Programming Language :: Python :: 3
Classifier: Programming Language :: Python :: 3.8
Classifier: Programming Language :: Python :: 3.9
Classifier: Programming Language :: Python :: 3.10
Classifier: Programming Language :: Python :: 3.11
Classifier: Programming Language :: Python :: 3.12
Classifier: Programming Language :: Python :: 3.13
Requires-Dist: msgpack (>=1.0.3,<2.0.0)
Requires-Dist: pydantic (>=2.0.3,<3.0.0)
Requires-Dist: requests (>=2.30.0,<3.0.0)
Requires-Dist: sseclient-py (>=1.7.2,<2.0.0)
Project-URL: Documentation, https://alpaca.markets/docs/python-sdk/
Project-URL: Repository, https://github.com/nrcrews/alpaca-py-slim
